BruteBuster/__init__.py
BruteBuster/admin.py
BruteBuster/apps.py
BruteBuster/decorators.py
BruteBuster/middleware.py
BruteBuster/models.py
django_brutebuster2-0.2.0.dist-info/LICENSE
django_brutebuster2-0.2.0.dist-info/METADATA
django_brutebuster2-0.2.0.dist-info/WHEEL
django_brutebuster2-0.2.0.dist-info/top_level.txt
django_brutebuster2-0.2.0.dist-info/RECORD
