Metadata-Version: 2.1
Name: django-brutebuster2
Version: 0.2.0
Summary: Django Bruteforce Buster
Home-page: https://github.com/mtrdesign/django-brutebuster/
Author: MTR Design
Author-email: office@mtr-design.com
License: UNKNOWN
Platform: UNKNOWN
Classifier: Programming Language :: Python :: 3
Classifier: License :: OSI Approved :: MIT License
Classifier: Operating System :: OS Independent
